[
    {
        "companyName": "慧川智能 (Hunch.AI)",
        "salary": "13k-20k",
        "position": "杭州・西湖区"
    },
    {
        "companyName": "云间网络",
        "salary": "10k-15k",
        "position": "成都・紫荆"
    },
    {
        "companyName": "华软科技",
        "salary": "11k-20k",
        "position": "西安・高新技…"
    },
    {
        "companyName": "微视互动",
        "salary": "8k-13k",
        "position": "武汉・关山"
    },
    {
        "companyName": "梦享网络",
        "salary": "13k-25k",
        "position": "深圳・深圳湾"
    },
    {
        "companyName": "战神联盟",
        "salary": "10k-18k",
        "position": "广州・员村"
    },
    {
        "companyName": "贝多分金融",
        "salary": "15k-25k",
        "position": "深圳・下沙"
    },
    {
        "companyName": "前海农交所",
        "salary": "15k-30k",
        "position": "深圳・深圳湾"
    },
    {
        "companyName": "源石云",
        "salary": "10k-20k",
        "position": "上海・漕宝路"
    },
    {
        "companyName": "广通软件",
        "salary": "10k-20k",
        "position": "杭州・文一路"
    },
    {
        "companyName": "南天",
        "salary": "8k-15k",
        "position": "广州・天河区"
    },
    {
        "companyName": "千寻万物",
        "salary": "10k-20k",
        "position": "深圳・科技园"
    },
    {
        "companyName": "披云科技",
        "salary": "8k-11k",
        "position": "南京・建邺区"
    },
    {
        "companyName": "通力互联",
        "salary": "13k-25k",
        "position": "深圳・坂田"
    },
    {
        "companyName": "微侠",
        "salary": "18k-25k",
        "position": "上海・长宁区"
    },
    {
        "companyName": "通力互联",
        "salary": "9k-18k",
        "position": "成都・锦江区"
    },
    {
        "companyName": "迅联网络",
        "salary": "5k-10k",
        "position": "青岛・黄岛区"
    },
    {
        "companyName": "皙印",
        "salary": "8k-12k",
        "position": "厦门・思明区"
    },
    {
        "companyName": "无锡聚云科技有限公司",
        "salary": "6k-12k",
        "position": "无锡・滨湖区"
    },
    {
        "companyName": "钱咖",
        "salary": "15k-20k",
        "position": "上海・十六铺"
    },
    {
        "companyName": "波德林智能科技",
        "salary": "10k-15k",
        "position": "厦门・思明区"
    },
    {
        "companyName": "融科数据",
        "salary": "8k-12k",
        "position": "济南・高新区"
    },
    {
        "companyName": "点亿汽车科技",
        "salary": "15k-20k",
        "position": "广州・番禺区"
    },
    {
        "companyName": "安博伟业",
        "salary": "4k-8k",
        "position": "天津・气象台…"
    },
    {
        "companyName": "中继科技",
        "salary": "7k-12k",
        "position": "长沙・麓谷"
    },
    {
        "companyName": "重庆足下科技",
        "salary": "12k-14k",
        "position": "成都・紫荆"
    },
    {
        "companyName": "上海中软华腾软件系统有限公司",
        "salary": "14k-20k",
        "position": "深圳・大冲"
    },
    {
        "companyName": "全速网络",
        "salary": "16k-20k",
        "position": "杭州・拱墅区"
    },
    {
        "companyName": "成都钱方",
        "salary": "12k-20k",
        "position": "成都・华阳"
    },
    {
        "companyName": "乐飞天下",
        "salary": "15k-25k",
        "position": "北京・大望路"
    },
    {
        "companyName": "通力互联",
        "salary": "9k-18k",
        "position": "北京・北京大…"
    },
    {
        "companyName": "金证股份",
        "salary": "10k-20k",
        "position": "北京・亮马桥"
    },
    {
        "companyName": "Tanment",
        "salary": "20k-30k",
        "position": "深圳・南油"
    },
    {
        "companyName": "eBrain",
        "salary": "15k-25k",
        "position": "北京・朝阳区"
    },
    {
        "companyName": "智信锐捷",
        "salary": "6k-11k",
        "position": "成都・牛王庙"
    },
    {
        "companyName": "动脑科技",
        "salary": "10k-20k",
        "position": "长沙・岳麓区"
    },
    {
        "companyName": "聚微",
        "salary": "12k-24k",
        "position": "北京・白石桥"
    },
    {
        "companyName": "北京飞博教育科技股份有限公司",
        "salary": "20k-25k",
        "position": "北京・双井"
    },
    {
        "companyName": "海万科技",
        "salary": "10k-20k",
        "position": "深圳・新洲"
    },
    {
        "companyName": "易派软件",
        "salary": "7k-14k",
        "position": "西安・雁塔区"
    },
    {
        "companyName": "享睡空间",
        "salary": "10k-20k",
        "position": "北京・东城区"
    },
    {
        "companyName": "童程童美",
        "salary": "6k-8k",
        "position": "天津・白堤路"
    },
    {
        "companyName": "广州指趣",
        "salary": "15k-25k",
        "position": "广州・车陂"
    },
    {
        "companyName": "Techmahindra",
        "salary": "10k-15k",
        "position": "深圳・坂田"
    },
    {
        "companyName": "MOLBASE",
        "salary": "10k-18k",
        "position": "上海・虹梅路"
    },
    {
        "companyName": "金证股份",
        "salary": "10k-15k",
        "position": "北京・亮马桥"
    },
    {
        "companyName": "海万科技",
        "salary": "8k-15k",
        "position": "深圳・福田区"
    },
    {
        "companyName": "小怪兽",
        "salary": "8k-15k",
        "position": "大连・凌水"
    },
    {
        "companyName": "有利网",
        "salary": "15k-25k",
        "position": "成都・玉林"
    },
    {
        "companyName": "点融",
        "salary": "18k-25k",
        "position": "上海・五里桥"
    },
    {
        "companyName": "中讯汉扬",
        "salary": "13k-20k",
        "position": "深圳・白石洲"
    },
    {
        "companyName": "松茂科技",
        "salary": "12k-18k",
        "position": "深圳・前海"
    },
    {
        "companyName": "会搜股份",
        "salary": "12k-24k",
        "position": "杭州・江干区"
    },
    {
        "companyName": "百布",
        "salary": "15k-28k",
        "position": "广州・瑞宝"
    },
    {
        "companyName": "虎赞科技",
        "salary": "10k-20k",
        "position": "福州・金山"
    },
    {
        "companyName": "上海提捺信息科技有限...",
        "salary": "20k-30k",
        "position": "深圳・科技园"
    },
    {
        "companyName": "旷视MEGVII",
        "salary": "20k-30k",
        "position": "北京・北京大…"
    },
    {
        "companyName": "生学教育",
        "salary": "20k-30k",
        "position": "成都・高新区"
    },
    {
        "companyName": "Bespin Global China",
        "salary": "15k-30k",
        "position": "北京・朝阳区"
    },
    {
        "companyName": "链友科技",
        "salary": "10k-20k",
        "position": "广州・棠下"
    },
    {
        "companyName": "海万科技",
        "salary": "13k-25k",
        "position": "深圳・亮马桥"
    },
    {
        "companyName": "点融",
        "salary": "18k-25k",
        "position": "上海・五里桥"
    },
    {
        "companyName": "AI考拉",
        "salary": "20k-35k",
        "position": "广州・海珠区"
    },
    {
        "companyName": "富Z科技",
        "salary": "10k-18k",
        "position": "深圳・深圳湾"
    },
    {
        "companyName": "校宝在线",
        "salary": "15k-25k",
        "position": "杭州・文三路"
    },
    {
        "companyName": "矩阵元",
        "salary": "15k-30k",
        "position": "深圳・南油"
    },
    {
        "companyName": "杭州祖玛",
        "salary": "15k-30k",
        "position": "杭州・西溪"
    },
    {
        "companyName": "跨越速运",
        "salary": "30k-35k",
        "position": "深圳・南油"
    },
    {
        "companyName": "杭州雅拓",
        "salary": "10k-20k",
        "position": "杭州・文二路"
    },
    {
        "companyName": "紫川软件",
        "salary": "10k-15k",
        "position": "深圳・前海"
    },
    {
        "companyName": "中睿天下",
        "salary": "6k-12k",
        "position": "济南・舜耕路"
    },
    {
        "companyName": "企朋",
        "salary": "15k-25k",
        "position": "杭州・西溪"
    },
    {
        "companyName": "江民",
        "salary": "10k-20k",
        "position": "北京・海淀区"
    },
    {
        "companyName": "虎扑",
        "salary": "20k-35k",
        "position": "上海・虹口足…"
    },
    {
        "companyName": "荔枝",
        "salary": "10k-20k",
        "position": "广州・天河区"
    },
    {
        "companyName": "校宝在线",
        "salary": "15k-30k",
        "position": "杭州・文三路"
    },
    {
        "companyName": "洋葱omall",
        "salary": "18k-24k",
        "position": "广州・天河区"
    },
    {
        "companyName": "展游",
        "salary": "15k-25k",
        "position": "北京・海淀区"
    },
    {
        "companyName": "粉象生活",
        "salary": "12k-18k",
        "position": "杭州・西湖区"
    },
    {
        "companyName": "绿智汇",
        "salary": "10k-15k",
        "position": "上海・中原"
    },
    {
        "companyName": "南天",
        "salary": "10k-20k",
        "position": "广州・天河区"
    },
    {
        "companyName": "明源云",
        "salary": "13k-23k",
        "position": "深圳・深圳湾"
    },
    {
        "companyName": "弘度科技",
        "salary": "15k-25k",
        "position": "广州・广卫"
    },
    {
        "companyName": "河流道",
        "salary": "8k-15k",
        "position": "济南・高新区"
    },
    {
        "companyName": "富Z科技",
        "salary": "8k-15k",
        "position": "广州・珠江新…"
    },
    {
        "companyName": "驴迹导游",
        "salary": "10k-18k",
        "position": "广州・天河区"
    },
    {
        "companyName": "天上友嘉",
        "salary": "10k-20k",
        "position": "成都・高新区"
    },
    {
        "companyName": "中标软件",
        "salary": "10k-20k",
        "position": "北京・海淀区"
    },
    {
        "companyName": "维拓利亚",
        "salary": "9k-13k",
        "position": "深圳・科技园"
    },
    {
        "companyName": "魔筷科技",
        "salary": "15k-20k",
        "position": "杭州・仓前"
    },
    {
        "companyName": "2144游戏",
        "salary": "15k-30k",
        "position": "上海・张江"
    },
    {
        "companyName": "爱乐奇",
        "salary": "15k-30k",
        "position": "上海・张江"
    },
    {
        "companyName": "链神科技",
        "salary": "25k-50k",
        "position": "广州・员村"
    },
    {
        "companyName": "盛趣时代",
        "salary": "12k-20k",
        "position": "成都・火车南…"
    },
    {
        "companyName": "霖梓控股",
        "salary": "10k-20k",
        "position": "杭州・江南"
    },
    {
        "companyName": "英语趣配音",
        "salary": "15k-20k",
        "position": "杭州・西兴"
    },
    {
        "companyName": "乐约健康",
        "salary": "15k-30k",
        "position": "北京・东城区"
    },
    {
        "companyName": "亚美",
        "salary": "10k-15k",
        "position": "广州・天河区"
    },
    {
        "companyName": "神州商龙",
        "salary": "10k-15k",
        "position": "天津・南开区"
    },
    {
        "companyName": "高新网络科技",
        "salary": "10k-20k",
        "position": "长沙・岳麓区"
    },
    {
        "companyName": "慕课网",
        "salary": "15k-25k",
        "position": "北京・海淀区"
    },
    {
        "companyName": "阔知网络",
        "salary": "9k-15k",
        "position": "杭州・浦沿"
    },
    {
        "companyName": "腾讯",
        "salary": "20k-40k",
        "position": "深圳・南油"
    },
    {
        "companyName": "飞贷金融科技",
        "salary": "20k-35k",
        "position": "深圳・科技园"
    },
    {
        "companyName": "绿瘦集团",
        "salary": "15k-20k",
        "position": "广州・芳村"
    },
    {
        "companyName": "好省",
        "salary": "15k-25k",
        "position": "杭州・西湖区"
    },
    {
        "companyName": "慕课网",
        "salary": "15k-30k",
        "position": "北京・中关村"
    },
    {
        "companyName": "哈出行",
        "salary": "15k-25k",
        "position": "上海・闵行区"
    },
    {
        "companyName": "晟运通科技",
        "salary": "15k-25k",
        "position": "西安・科技二…"
    },
    {
        "companyName": "凡科",
        "salary": "16k-22k",
        "position": "广州・工业大…"
    },
    {
        "companyName": "毒APP",
        "salary": "20k-35k",
        "position": "上海・虹口足…"
    },
    {
        "companyName": "博奥特科技",
        "salary": "14k-18k",
        "position": "上海・洋泾"
    },
    {
        "companyName": "Bespin Global China",
        "salary": "15k-30k",
        "position": "北京・朝阳区"
    },
    {
        "companyName": "中建电商",
        "salary": "15k-30k",
        "position": "北京・甘家口"
    },
    {
        "companyName": "易路",
        "salary": "10k-20k",
        "position": "成都・高新区"
    },
    {
        "companyName": "好未来",
        "salary": "25k-40k",
        "position": "北京・北京大…"
    },
    {
        "companyName": "三少猩球",
        "salary": "16k-22k",
        "position": "上海・新闸路"
    },
    {
        "companyName": "第一波",
        "salary": "20k-30k",
        "position": "深圳・大冲"
    },
    {
        "companyName": "逍邦",
        "salary": "9k-18k",
        "position": "杭州・江南"
    },
    {
        "companyName": "CmsTop",
        "salary": "10k-20k",
        "position": "武汉・关山"
    },
    {
        "companyName": "好省",
        "salary": "15k-25k",
        "position": "杭州・西湖区"
    },
    {
        "companyName": "微屏游戏",
        "salary": "18k-25k",
        "position": "上海・浦东新…"
    },
    {
        "companyName": "广府数字",
        "salary": "25k-50k",
        "position": "广州・东圃"
    },
    {
        "companyName": "金十数据",
        "salary": "15k-30k",
        "position": "广州・海珠区"
    },
    {
        "companyName": "方趣网络",
        "salary": "20k-30k",
        "position": "上海・闵行区"
    },
    {
        "companyName": "原力互娱",
        "salary": "12k-20k",
        "position": "广州・员村"
    },
    {
        "companyName": "AAM中国",
        "salary": "14k-22k",
        "position": "广州・荔湾区"
    },
    {
        "companyName": "威富通",
        "salary": "12k-18k",
        "position": "深圳・科技园"
    },
    {
        "companyName": "同程艺龙",
        "salary": "25k-45k",
        "position": "北京・大山子"
    },
    {
        "companyName": "象聚集团",
        "salary": "15k-20k",
        "position": "郑州・高新区"
    },
    {
        "companyName": "峰途网络",
        "salary": "16k-28k",
        "position": "上海・静安寺"
    },
    {
        "companyName": "毒APP",
        "salary": "25k-35k",
        "position": "上海・虹口足…"
    },
    {
        "companyName": "广州棒谷科技股份有限公司",
        "salary": "10k-20k",
        "position": "广州・同德"
    },
    {
        "companyName": "华米科技",
        "salary": "10k-20k",
        "position": "合肥・高新区"
    },
    {
        "companyName": "海万科技",
        "salary": "10k-20k",
        "position": "深圳・福田区"
    },
    {
        "companyName": "金十数据",
        "salary": "12k-20k",
        "position": "广州・海珠区"
    },
    {
        "companyName": "华米科技",
        "salary": "10k-20k",
        "position": "合肥・高新区"
    },
    {
        "companyName": "方趣网络",
        "salary": "18k-25k",
        "position": "上海・闵行区"
    },
    {
        "companyName": "上海中软华腾软件系统有限公司",
        "salary": "12k-18k",
        "position": "佛山・桂城"
    },
    {
        "companyName": "德邦",
        "salary": "15k-19k",
        "position": "上海・青浦区"
    },
    {
        "companyName": "海万科技",
        "salary": "10k-20k",
        "position": "上海・洋泾"
    },
    {
        "companyName": "中电健康云",
        "salary": "24k-48k",
        "position": "成都・武侯区"
    },
    {
        "companyName": "时速云",
        "salary": "10k-18k",
        "position": "北京・学院路"
    },
    {
        "companyName": "魔方公寓",
        "salary": "15k-20k",
        "position": "上海・虹桥"
    },
    {
        "companyName": "紫川软件",
        "salary": "12k-15k",
        "position": "深圳・科技园"
    },
    {
        "companyName": "华云数据",
        "salary": "15k-30k",
        "position": "上海・复旦大…"
    },
    {
        "companyName": "青藤云安全",
        "salary": "10k-20k",
        "position": "武汉・东湖新…"
    },
    {
        "companyName": "龙渊网络",
        "salary": "10k-20k",
        "position": "成都・高新区"
    },
    {
        "companyName": "共享伞：漂流伞mobrella",
        "salary": "13k-18k",
        "position": "杭州・文三路"
    },
    {
        "companyName": "盛世锦天",
        "salary": "15k-30k",
        "position": "上海・普陀区"
    },
    {
        "companyName": "海万科技",
        "salary": "9k-11k",
        "position": "上海・徐汇区"
    },
    {
        "companyName": "上海中软华腾软件系统有限公司",
        "salary": "10k-15k",
        "position": "佛山・桂城"
    },
    {
        "companyName": "紫川软件",
        "salary": "8k-13k",
        "position": "深圳・新洲"
    },
    {
        "companyName": "时速云",
        "salary": "15k-25k",
        "position": "广州・天河区"
    },
    {
        "companyName": "安恒信息",
        "salary": "10k-20k",
        "position": "杭州・西兴"
    },
    {
        "companyName": "港优创新",
        "salary": "15k-25k",
        "position": "深圳・大冲"
    },
    {
        "companyName": "上海只二网络科技有限公司",
        "salary": "15k-25k",
        "position": "上海・浦东新…"
    },
    {
        "companyName": "誉存科技",
        "salary": "8k-16k",
        "position": "重庆・渝北区"
    },
    {
        "companyName": "对庄科技",
        "salary": "10k-15k",
        "position": "广州・沙面"
    },
    {
        "companyName": "天傲网络科技",
        "salary": "8k-15k",
        "position": "成都・武侯区"
    },
    {
        "companyName": "YIDATEC",
        "salary": "13k-19k",
        "position": "广州・员村"
    },
    {
        "companyName": "跨越速运",
        "salary": "18k-30k",
        "position": "深圳・南油"
    },
    {
        "companyName": "武汉佰钧成技术有限公司",
        "salary": "10k-15k",
        "position": "杭州・西湖区"
    },
    {
        "companyName": "宝能百货零售",
        "salary": "15k-25k",
        "position": "深圳・罗湖区"
    },
    {
        "companyName": "盛世锦天",
        "salary": "15k-30k",
        "position": "上海・普陀区"
    },
    {
        "companyName": "海万科技",
        "salary": "12k-18k",
        "position": "上海・龙华"
    },
    {
        "companyName": "紫川软件",
        "salary": "10k-20k",
        "position": "深圳・新洲"
    },
    {
        "companyName": "安恒信息",
        "salary": "10k-20k",
        "position": "济南・高新区"
    },
    {
        "companyName": "港优创新",
        "salary": "9k-13k",
        "position": "深圳・大冲"
    },
    {
        "companyName": "跨越速运",
        "salary": "15k-25k",
        "position": "深圳・南油"
    },
    {
        "companyName": "深圳微融",
        "salary": "14k-22k",
        "position": "深圳・科技园"
    },
    {
        "companyName": "捷顺科技股份",
        "salary": "13k-18k",
        "position": "深圳・下梅林"
    },
    {
        "companyName": "PaaSoo 无限云科技",
        "salary": "8k-12k",
        "position": "厦门・思明区"
    },
    {
        "companyName": "万普瑞邦",
        "salary": "8k-16k",
        "position": "深圳・南山区"
    },
    {
        "companyName": "美平米",
        "salary": "10k-15k",
        "position": "杭州・四季青"
    },
    {
        "companyName": "乐约健康",
        "salary": "8k-10k",
        "position": "武汉・徐东"
    },
    {
        "companyName": "艾姆诗（IMC）",
        "salary": "12k-24k",
        "position": "深圳・龙华新…"
    },
    {
        "companyName": "虎扑",
        "salary": "20k-30k",
        "position": "上海・虹口足…"
    },
    {
        "companyName": "广联储社群",
        "salary": "8k-12k",
        "position": "深圳・科技园"
    },
    {
        "companyName": "贝嘟科技",
        "salary": "8k-12k",
        "position": "杭州・高教园"
    },
    {
        "companyName": "海万科技",
        "salary": "10k-20k",
        "position": "深圳・福田区"
    },
    {
        "companyName": "安恒信息",
        "salary": "10k-20k",
        "position": "上海・中山公…"
    },
    {
        "companyName": "捷顺科技股份",
        "salary": "16k-22k",
        "position": "深圳・上梅林"
    },
    {
        "companyName": "乐约健康",
        "salary": "10k-15k",
        "position": "北京・东城区"
    },
    {
        "companyName": "大淘客",
        "salary": "7k-11k",
        "position": "成都・华阳"
    },
    {
        "companyName": "YIDATEC",
        "salary": "10k-17k",
        "position": "广州・员村"
    },
    {
        "companyName": "楚楚街",
        "salary": "15k-20k",
        "position": "北京・海淀区"
    },
    {
        "companyName": "硅基智能",
        "salary": "10k-20k",
        "position": "南京・雨花台…"
    },
    {
        "companyName": "2144游戏",
        "salary": "15k-30k",
        "position": "上海・张江"
    },
    {
        "companyName": "君合创胜",
        "salary": "9k-15k",
        "position": "上海・新闸路"
    },
    {
        "companyName": "中非网",
        "salary": "10k-15k",
        "position": "成都・武侯区"
    },
    {
        "companyName": "亚美",
        "salary": "15k-25k",
        "position": "广州・天河区"
    },
    {
        "companyName": "安豆科技",
        "salary": "15k-20k",
        "position": "广州・天河区"
    },
    {
        "companyName": "DeNA China",
        "salary": "12k-18k",
        "position": "上海・大连"
    },
    {
        "companyName": "天傲网络科技",
        "salary": "8k-15k",
        "position": "成都・武侯区"
    },
    {
        "companyName": "安恒信息",
        "salary": "10k-20k",
        "position": "武汉・江滩"
    },
    {
        "companyName": "捷顺科技股份",
        "salary": "10k-15k",
        "position": "深圳・下梅林"
    },
    {
        "companyName": "跨越速运",
        "salary": "15k-25k",
        "position": "深圳・南油"
    },
    {
        "companyName": "神州优车集团",
        "salary": "20k-40k",
        "position": "北京・皂君庙"
    },
    {
        "companyName": "花色互娱",
        "salary": "10k-20k",
        "position": "深圳・南山区"
    },
    {
        "companyName": "利汇",
        "salary": "13k-20k",
        "position": "深圳・南山区"
    },
    {
        "companyName": "武汉佰钧成技术有限公司",
        "salary": "9K-14K",
        "position": "深圳・南山区"
    },
    {
        "companyName": "战神联盟",
        "salary": "13k-25k",
        "position": "广州・员村"
    },
    {
        "companyName": "尚瑜科技",
        "salary": "8k-12k",
        "position": "广州・天河区"
    },
    {
        "companyName": "星巢网络",
        "salary": "20k-30k",
        "position": "杭州・西溪"
    },
    {
        "companyName": "微租",
        "salary": "8k-13k",
        "position": "广州・市桥"
    },
    {
        "companyName": "杰夫与友",
        "salary": "6k-8k",
        "position": "重庆・七星岗"
    },
    {
        "companyName": "店家科技",
        "salary": "15k-25k",
        "position": "杭州・西湖区"
    },
    {
        "companyName": "东方财富",
        "salary": "10k-20k",
        "position": "上海・龙华"
    },
    {
        "companyName": "小鸟云",
        "salary": "12k-20k",
        "position": "深圳・南山区"
    },
    {
        "companyName": "艾美网络科技",
        "salary": "25k-45k",
        "position": "广州・番禺区"
    },
    {
        "companyName": "YIDATEC",
        "salary": "10k-13k",
        "position": "深圳・前海"
    },
    {
        "companyName": "申通快递",
        "salary": "13k-24k",
        "position": "上海・重固"
    },
    {
        "companyName": "绯闻网络",
        "salary": "8k-11k",
        "position": "苏州・木渎"
    },
    {
        "companyName": "安久科技",
        "salary": "9k-18k",
        "position": "广州・黄村"
    },
    {
        "companyName": "明源云",
        "salary": "10k-18k",
        "position": "深圳・深圳湾"
    },
    {
        "companyName": "天傲网络科技",
        "salary": "8k-15k",
        "position": "成都・武侯区"
    },
    {
        "companyName": "映潮科技",
        "salary": "6k-12k",
        "position": "成都・高新区"
    },
    {
        "companyName": "链友科技",
        "salary": "14k-20k",
        "position": "广州・棠下"
    },
    {
        "companyName": "武汉掌中宝",
        "salary": "8k-13k",
        "position": "武汉・南湖"
    },
    {
        "companyName": "百布",
        "salary": "10k-18k",
        "position": "广州・瑞宝"
    },
    {
        "companyName": "RC PLATFORM",
        "salary": "15k-25k",
        "position": "北京・四惠"
    },
    {
        "companyName": "筷子科技",
        "salary": "10k-20k",
        "position": "广州・越秀区"
    },
    {
        "companyName": "优倍快 (UBNT)",
        "salary": "13k-25k",
        "position": "厦门・思明区"
    },
    {
        "companyName": "蓝色速度",
        "salary": "15k-20k",
        "position": "深圳・车公庙"
    },
    {
        "companyName": "奇异果科技",
        "salary": "15k-25k",
        "position": "广州・客村"
    },
    {
        "companyName": "彩晔科技",
        "salary": "6k-12k",
        "position": "南京・安德门"
    },
    {
        "companyName": "途虎养车网",
        "salary": "14k-28k",
        "position": "上海・南方商…"
    },
    {
        "companyName": "立创商城",
        "salary": "15k-20k",
        "position": "深圳・香蜜湖"
    },
    {
        "companyName": "光娱游戏",
        "salary": "18k-28k",
        "position": "广州・岗顶"
    },
    {
        "companyName": "伴鱼口语",
        "salary": "40k-70k",
        "position": "北京・亚运村"
    },
    {
        "companyName": "盛裕宏科技",
        "salary": "15k-25k",
        "position": "成都・高新区"
    },
    {
        "companyName": "安恒信息",
        "salary": "10k-13k",
        "position": "杭州・西兴"
    },
    {
        "companyName": "高新网络科技",
        "salary": "15k-20k",
        "position": "深圳・西乡"
    },
    {
        "companyName": "YIDATEC",
        "salary": "10k-13k",
        "position": "深圳・深圳湾"
    },
    {
        "companyName": "腾讯",
        "salary": "20k-40k",
        "position": "深圳・南油"
    },
    {
        "companyName": "同程艺龙",
        "salary": "25k-45k",
        "position": "北京・大山子"
    },
    {
        "companyName": "深圳市软信通网络科技有限公司",
        "salary": "8k-12k",
        "position": "深圳・后海"
    },
    {
        "companyName": "子不语",
        "salary": "15k-21k",
        "position": "杭州・南苑"
    },
    {
        "companyName": "新旦股份",
        "salary": "15k-18k",
        "position": "上海・龙华"
    },
    {
        "companyName": "知识星球",
        "salary": "15k-30k",
        "position": "深圳・科技园"
    },
    {
        "companyName": "得见科技",
        "salary": "7k-9k",
        "position": "武汉・武昌区"
    },
    {
        "companyName": "上海瑞阙文化发展有限公司",
        "salary": "20k-35k",
        "position": "上海・黄浦区"
    },
    {
        "companyName": "中继科技",
        "salary": "8k-16k",
        "position": "长沙・岳麓区"
    },
    {
        "companyName": "乐盟",
        "salary": "20k-40k",
        "position": "深圳・大冲"
    },
    {
        "companyName": "大象游戏",
        "salary": "20k-25k",
        "position": "深圳・南山区"
    },
    {
        "companyName": "艾鑫承",
        "salary": "10k-12k",
        "position": "深圳・白石洲"
    },
    {
        "companyName": "申通快递",
        "salary": "10k-20k",
        "position": "上海・重固"
    },
    {
        "companyName": "科来软件",
        "salary": "8k-15k",
        "position": "北京・西二旗"
    },
    {
        "companyName": "高奈特",
        "salary": "15k-20k",
        "position": "广州・荔湾区"
    },
    {
        "companyName": "车音智能",
        "salary": "15k-25k",
        "position": "北京・安定门"
    },
    {
        "companyName": "阳光康众",
        "salary": "10k-15k",
        "position": "广州・海珠区"
    },
    {
        "companyName": "朗新科技",
        "salary": "10k-20k",
        "position": "杭州・西溪"
    },
    {
        "companyName": "店家科技",
        "salary": "15k-25k",
        "position": "杭州・余杭区"
    },
    {
        "companyName": "卖座网",
        "salary": "12k-18k",
        "position": "深圳・科技园"
    },
    {
        "companyName": "房大办公",
        "salary": "10k-15k",
        "position": "上海・打浦桥"
    },
    {
        "companyName": "网新华通",
        "salary": "10k-15k",
        "position": "杭州・西溪"
    },
    {
        "companyName": "浦发卡中心",
        "salary": "25k-35k",
        "position": "上海・浦东新…"
    },
    {
        "companyName": "善行（深圳）系统有限公司",
        "salary": "15k-20k",
        "position": "深圳・科技园"
    },
    {
        "companyName": "广州多融信息科技有限公司",
        "salary": "10k-15k",
        "position": "广州・天河区"
    },
    {
        "companyName": "师悦科技",
        "salary": "8k-16k",
        "position": "西安・经济技…"
    },
    {
        "companyName": "CmsTop",
        "salary": "15k-25k",
        "position": "武汉・关山"
    },
    {
        "companyName": "星飞",
        "salary": "15k-30k",
        "position": "广州・天河区"
    },
    {
        "companyName": "道一云",
        "salary": "7k-14k",
        "position": "长沙・雨花区…"
    },
    {
        "companyName": "裕宁科技",
        "salary": "10k-18k",
        "position": "深圳・深圳湾"
    },
    {
        "companyName": "58到家",
        "salary": "15k-30k",
        "position": "北京・北苑"
    },
    {
        "companyName": "上海你我贷互联网金融信息服务",
        "salary": "20k-40k",
        "position": "上海・东方路"
    },
    {
        "companyName": "知识星球",
        "salary": "15k-30k",
        "position": "深圳・科技园"
    },
    {
        "companyName": "广通软件",
        "salary": "10k-20k",
        "position": "杭州・翠苑"
    },
    {
        "companyName": "阿里文娱",
        "salary": "20k-40k",
        "position": "广州・员村"
    },
    {
        "companyName": "浦发卡中心",
        "salary": "15k-25k",
        "position": "上海・浦东新…"
    },
    {
        "companyName": "道一云",
        "salary": "10k-15k",
        "position": "广州・天河公…"
    },
    {
        "companyName": "尤达科技",
        "salary": "10k-20k",
        "position": "广州・海珠区"
    },
    {
        "companyName": "诚智天扬",
        "salary": "9k-15k",
        "position": "杭州・高新文…"
    },
    {
        "companyName": "卡友北分",
        "salary": "12k-18k",
        "position": "北京・双井"
    },
    {
        "companyName": "淘集集",
        "salary": "20k-30k",
        "position": "上海・静安区"
    },
    {
        "companyName": "博悦科创",
        "salary": "10k-16k",
        "position": "上海・唐镇"
    },
    {
        "companyName": "浙江钱兔网络科技有限公司",
        "salary": "13k-26k",
        "position": "杭州・萧山区"
    },
    {
        "companyName": "点购商城",
        "salary": "15k-25k",
        "position": "广州・天园"
    },
    {
        "companyName": "华讯",
        "salary": "10k-19k",
        "position": "福州・闽侯县"
    },
    {
        "companyName": "易佰网络科技",
        "salary": "20k-30k",
        "position": "深圳・龙岗区"
    },
    {
        "companyName": "奇异果科技",
        "salary": "15k-20k",
        "position": "广州・客村"
    },
    {
        "companyName": "优维科技",
        "salary": "8k-13k",
        "position": "济南・历下区"
    },
    {
        "companyName": "懒人听书",
        "salary": "12k-24k",
        "position": "深圳・大冲"
    },
    {
        "companyName": "GeexFinance",
        "salary": "10k-20k",
        "position": "上海・杨浦区"
    },
    {
        "companyName": "道一云",
        "salary": "10k-15k",
        "position": "梅州・梅江区"
    },
    {
        "companyName": "优维科技",
        "salary": "15k-25k",
        "position": "北京・望京"
    },
    {
        "companyName": "网易",
        "salary": "15k-30k",
        "position": "广州・冼村"
    },
    {
        "companyName": "广州绿森",
        "salary": "10k-15k",
        "position": "广州・番禺区"
    },
    {
        "companyName": "海万科技",
        "salary": "15k-20k",
        "position": "上海・静安区"
    },
    {
        "companyName": "维格英科技",
        "salary": "8k-12k",
        "position": "武汉・杨园"
    },
    {
        "companyName": "斐珞尔",
        "salary": "10k-15k",
        "position": "上海・徐家汇"
    },
    {
        "companyName": "炎龙科技",
        "salary": "13k-20k",
        "position": "长沙・岳麓区"
    },
    {
        "companyName": "深圳米趣玩科技有限公司",
        "salary": "10k-15k",
        "position": "深圳・深圳湾"
    },
    {
        "companyName": "51JOB",
        "salary": "10k-20k",
        "position": "上海・张江"
    },
    {
        "companyName": "腾讯",
        "salary": "18k-30k",
        "position": "深圳・南山区"
    },
    {
        "companyName": "脸脸",
        "salary": "8k-10k",
        "position": "杭州・余杭区"
    },
    {
        "companyName": "云间网络",
        "salary": "8k-12k",
        "position": "广州・广卫"
    },
    {
        "companyName": "蜂融网络",
        "salary": "25k-50k",
        "position": "杭州・西溪"
    },
    {
        "companyName": "联元智能科技",
        "salary": "15k-30k",
        "position": "上海・曹杨"
    },
    {
        "companyName": "道一云",
        "salary": "10k-15k",
        "position": "北京・安定门"
    },
    {
        "companyName": "掌众集团",
        "salary": "12k-18k",
        "position": "北京・海淀区"
    },
    {
        "companyName": "搜房宝",
        "salary": "20k-40k",
        "position": "深圳・科技园"
    },
    {
        "companyName": "灵雀云",
        "salary": "10k-20k",
        "position": "上海・静安区"
    },
    {
        "companyName": "税友软件",
        "salary": "15k-25k",
        "position": "杭州・开发区"
    },
    {
        "companyName": "Majorsec",
        "salary": "10k-18k",
        "position": "北京・和平里"
    },
    {
        "companyName": "中科祥云",
        "salary": "8k-10k",
        "position": "上海・虹梅路"
    },
    {
        "companyName": "宅急送",
        "salary": "10k-20k",
        "position": "北京・后沙峪"
    },
    {
        "companyName": "摘星者",
        "salary": "12k-18k",
        "position": "广州・赤岗"
    },
    {
        "companyName": "暴雪奇迹",
        "salary": "7k-13k",
        "position": "深圳・南山区"
    },
    {
        "companyName": "软帝联合",
        "salary": "10k-15k",
        "position": "武汉・流芳"
    },
    {
        "companyName": "象盒科技",
        "salary": "10k-16k",
        "position": "长沙・东塘"
    },
    {
        "companyName": "亚飞电子",
        "salary": "15k-22k",
        "position": "深圳・坂田"
    },
    {
        "companyName": "微拍堂",
        "salary": "15k-30k",
        "position": "杭州・西湖"
    },
    {
        "companyName": "RC PLATFORM",
        "salary": "19k-30k",
        "position": "北京・八里庄"
    },
    {
        "companyName": "灵雀云",
        "salary": "10k-20k",
        "position": "深圳・科技园"
    },
    {
        "companyName": "北京中交兴路车联网科技有限公司",
        "salary": "15k-20k",
        "position": "北京・海淀区"
    },
    {
        "companyName": "魔方公寓",
        "salary": "15k-20k",
        "position": "上海・闵行区"
    },
    {
        "companyName": "小怪兽",
        "salary": "8k-15k",
        "position": "大连・凌水"
    },
    {
        "companyName": "湖南大简科技有限公司",
        "salary": "9k-16k",
        "position": "长沙・天心区"
    },
    {
        "companyName": "南方银谷",
        "salary": "10k-16k",
        "position": "上海・新天地"
    },
    {
        "companyName": "上海汇元通",
        "salary": "10k-20k",
        "position": "上海・四平路"
    },
    {
        "companyName": "众游科技",
        "salary": "15k-25k",
        "position": "深圳・南山区"
    },
    {
        "companyName": "健客网",
        "salary": "15k-30k",
        "position": "广州・萝岗区"
    },
    {
        "companyName": "优品财富管理有限公司",
        "salary": "7k-12k",
        "position": "武汉・流芳"
    },
    {
        "companyName": "瑞银信",
        "salary": "15k-30k",
        "position": "北京・朝阳区"
    },
    {
        "companyName": "康策网络",
        "salary": "10k-15k",
        "position": "杭州・仓前"
    },
    {
        "companyName": "巨人网络",
        "salary": "15k-25k",
        "position": "上海・松江区"
    },
    {
        "companyName": "墨云科技",
        "salary": "10k-20k",
        "position": "北京・上地"
    },
    {
        "companyName": "易铭",
        "salary": "13k-18k",
        "position": "杭州・复兴"
    },
    {
        "companyName": "南方银谷",
        "salary": "10k-16k",
        "position": "上海・黄浦区"
    },
    {
        "companyName": "生命奇点",
        "salary": "13k-24k",
        "position": "北京・海淀区"
    },
    {
        "companyName": "麒讯",
        "salary": "10k-20k",
        "position": "深圳・西丽"
    },
    {
        "companyName": "三优亲子",
        "salary": "8k-15k",
        "position": "广州・小北"
    },
    {
        "companyName": "申通快递",
        "salary": "12k-16k",
        "position": "上海・重固"
    },
    {
        "companyName": "金山办公软件",
        "salary": "18k-25k",
        "position": "广州・员村"
    },
    {
        "companyName": "君海游戏",
        "salary": "10k-18k",
        "position": "广州・海珠区"
    },
    {
        "companyName": "蓝色速度",
        "salary": "15k-25k",
        "position": "深圳・福田区"
    },
    {
        "companyName": "一起秀信息科技",
        "salary": "6k-10k",
        "position": "深圳・南油"
    },
    {
        "companyName": "上海你我贷互联网金融信息服务",
        "salary": "15k-25k",
        "position": "上海・东方路"
    },
    {
        "companyName": "小i机器人",
        "salary": "10k-15k",
        "position": "上海・江桥"
    },
    {
        "companyName": "北京八维研修学院",
        "salary": "15k-25k",
        "position": "北京・上地"
    },
    {
        "companyName": "长沙微领地网络科技有限公司",
        "salary": "10k-18k",
        "position": "长沙・麓谷"
    },
    {
        "companyName": "ZingFront智线",
        "salary": "6k-10k",
        "position": "武汉・关山"
    },
    {
        "companyName": "厦门约约出行科技有限公司",
        "salary": "10k-15k",
        "position": "厦门・思明区"
    },
    {
        "companyName": "动因体育",
        "salary": "20k-30k",
        "position": "北京・朝阳区"
    },
    {
        "companyName": "尤达科技",
        "salary": "15k-22k",
        "position": "广州・海珠区"
    },
    {
        "companyName": "湖北群艺",
        "salary": "10k-12k",
        "position": "广州・天河区"
    },
    {
        "companyName": "兆威机电",
        "salary": "12k-16k",
        "position": "深圳・宝安区"
    },
    {
        "companyName": "汉德森日用保健品（上海）有限公司",
        "salary": "15k-25k",
        "position": "上海・南京东…"
    },
    {
        "companyName": "通力互联",
        "salary": "8k-16k",
        "position": "深圳・大冲"
    },
    {
        "companyName": "哈出行",
        "salary": "12k-24k",
        "position": "上海・闵行区"
    },
    {
        "companyName": "税友软件",
        "salary": "12k-20k",
        "position": "杭州・滨江区"
    },
    {
        "companyName": "微友助手",
        "salary": "12k-24k",
        "position": "武汉・关山"
    },
    {
        "companyName": "数云",
        "salary": "10k-15k",
        "position": "西安・光华路"
    },
    {
        "companyName": "奇安信集团",
        "salary": "15k-30k",
        "position": "北京・朝阳区"
    },
    {
        "companyName": "酷萌网络（LNI技术有限公司）",
        "salary": "15k-25k",
        "position": "广州・岭南"
    },
    {
        "companyName": "快批KP",
        "salary": "25k-33k",
        "position": "广州・琶洲"
    },
    {
        "companyName": "尤米科技",
        "salary": "15k-25k",
        "position": "杭州・文二路"
    },
    {
        "companyName": "爱伙企业",
        "salary": "10k-15k",
        "position": "广州・大石"
    },
    {
        "companyName": "酷萌网络（LNI技术有限公司）",
        "salary": "15k-25k",
        "position": "上海・闵行区"
    },
    {
        "companyName": "哈出行",
        "salary": "13k-26k",
        "position": "上海・闵行区"
    },
    {
        "companyName": "广西德拓电子有限公司",
        "salary": "8k-15k",
        "position": "南宁・良庆区"
    },
    {
        "companyName": "掌数科技",
        "salary": "15k-25k",
        "position": "上海・浦东新…"
    },
    {
        "companyName": "艾速科技",
        "salary": "25k-30k",
        "position": "深圳・南山区"
    },
    {
        "companyName": "快批KP",
        "salary": "20k-30k",
        "position": "广州・琶洲"
    },
    {
        "companyName": "陕西华兆信息科技有限公司",
        "salary": "12k-20k",
        "position": "深圳・西丽"
    },
    {
        "companyName": "观眇生物科技",
        "salary": "15k-25k",
        "position": "杭州・天目山…"
    },
    {
        "companyName": "上海中软华腾软件系统有限公司",
        "salary": "12k-18k",
        "position": "深圳・振华路"
    },
    {
        "companyName": "学堂在线",
        "salary": "10k-20k",
        "position": "北京・五道口"
    },
    {
        "companyName": "上海喔趣",
        "salary": "10k-15k",
        "position": "无锡・新吴区"
    },
    {
        "companyName": "华云中盛",
        "salary": "14k-25k",
        "position": "深圳・南山区"
    },
    {
        "companyName": "掌尊科技",
        "salary": "12k-24k",
        "position": "杭州・古荡"
    },
    {
        "companyName": "紫讯科技",
        "salary": "8k-15k",
        "position": "福州・鼓楼区"
    },
    {
        "companyName": "校宝在线",
        "salary": "15k-30k",
        "position": "杭州・文一路"
    },
    {
        "companyName": "酷萌网络（LNI技术有限公司）",
        "salary": "15k-25k",
        "position": "深圳・大冲"
    },
    {
        "companyName": "波德林智能科技",
        "salary": "12k-20k",
        "position": "厦门・思明区"
    },
    {
        "companyName": "上海中软华腾软件系统有限公司",
        "salary": "15k-20k",
        "position": "上海・陆家嘴"
    },
    {
        "companyName": "IFEC",
        "salary": "12k-20k",
        "position": "广州・黄埔区"
    },
    {
        "companyName": "猫爸科技",
        "salary": "10k-15k",
        "position": "杭州・西兴"
    },
    {
        "companyName": "中科祥云",
        "salary": "6k-9k",
        "position": "广州・天河区"
    },
    {
        "companyName": "宝尊电商",
        "salary": "20k-35k",
        "position": "上海・闸北区"
    },
    {
        "companyName": "星蓝块链",
        "salary": "20k-40k",
        "position": "广州・天河区"
    },
    {
        "companyName": "广州果橙网络技术有限公司",
        "salary": "10k-15k",
        "position": "广州・天河区"
    },
    {
        "companyName": "广西德拓电子有限公司",
        "salary": "8k-15k",
        "position": "南宁・良庆区"
    },
    {
        "companyName": "君学",
        "salary": "18k-25k",
        "position": "上海・八佰伴"
    },
    {
        "companyName": "第一卫",
        "salary": "6k-12k",
        "position": "深圳・龙华新…"
    },
    {
        "companyName": "兄弟玩游戏/春秋游戏",
        "salary": "15k-20k",
        "position": "广州・天河公…"
    },
    {
        "companyName": "闪送",
        "salary": "20k-35k",
        "position": "北京・海淀区"
    },
    {
        "companyName": "润杨金融",
        "salary": "10k-20k",
        "position": "深圳・南山区"
    },
    {
        "companyName": "陌陌",
        "salary": "20k-40k",
        "position": "北京・望京"
    },
    {
        "companyName": "店佳科技",
        "salary": "9k-18k",
        "position": "北京・工体"
    },
    {
        "companyName": "合众易宝",
        "salary": "15k-25k",
        "position": "北京・四季青"
    },
    {
        "companyName": "长沙微领地网络科技有限公司",
        "salary": "9k-15k",
        "position": "长沙・麓谷"
    },
    {
        "companyName": "集和品牌",
        "salary": "8k-10k",
        "position": "广州・五羊新…"
    },
    {
        "companyName": "税友软件",
        "salary": "10k-20k",
        "position": "杭州・浦沿"
    },
    {
        "companyName": "众禄基金",
        "salary": "15k-25k",
        "position": "深圳・罗湖区"
    },
    {
        "companyName": "crosslink",
        "salary": "13k-18k",
        "position": "宁波・鄞州区"
    },
    {
        "companyName": "Xmov",
        "salary": "16k-30k",
        "position": "上海・徐汇区"
    },
    {
        "companyName": "中欧商业在线",
        "salary": "15k-20k",
        "position": "上海・金桥"
    },
    {
        "companyName": "金明源",
        "salary": "10k-20k",
        "position": "郑州・金水区"
    },
    {
        "companyName": "小鸟云",
        "salary": "13k-20k",
        "position": "深圳・南山区"
    },
    {
        "companyName": "五八到家",
        "salary": "15K-25K",
        "position": "长沙・麓谷"
    },
    {
        "companyName": "通力互联",
        "salary": "13k-24k",
        "position": "深圳・坂田"
    },
    {
        "companyName": "中国联保",
        "salary": "10k-15k",
        "position": "深圳・龙岗区"
    },
    {
        "companyName": "众禄基金",
        "salary": "15k-25k",
        "position": "深圳・罗湖区"
    },
    {
        "companyName": "搜道",
        "salary": "12k-24k",
        "position": "杭州・拱墅区"
    },
    {
        "companyName": "襄岳信息",
        "salary": "10K-20K",
        "position": "上海・控江路"
    },
    {
        "companyName": "皙印",
        "salary": "8k-12k",
        "position": "厦门・思明区"
    },
    {
        "companyName": "Q房网",
        "salary": "10k-18k",
        "position": "深圳・科技园"
    },
    {
        "companyName": "Swie.io",
        "salary": "14k-25k",
        "position": "北京・海淀区"
    },
    {
        "companyName": "广州小马网络科技有限公司",
        "salary": "13k-20k",
        "position": "广州・体育中…"
    },
    {
        "companyName": "全速网络",
        "salary": "10k-18k",
        "position": "杭州・湖墅南…"
    },
    {
        "companyName": "慧尔",
        "salary": "18k-22k",
        "position": "广州・东湖"
    },
    {
        "companyName": "拉趣科技",
        "salary": "12k-15k",
        "position": "杭州・西湖区"
    },
    {
        "companyName": "广州赤骥科技发展有限公司",
        "salary": "8k-13k",
        "position": "济南・杆石桥"
    },
    {
        "companyName": "亚安",
        "salary": "12k-15k",
        "position": "上海・四川北…"
    },
    {
        "companyName": "路路由",
        "salary": "10k-18k",
        "position": "上海・世纪公…"
    },
    {
        "companyName": "旗构旅游",
        "salary": "10k-15k",
        "position": "深圳・南山区"
    },
    {
        "companyName": "海万科技",
        "salary": "8k-14k",
        "position": "上海・张江"
    },
    {
        "companyName": "银兴科技",
        "salary": "13k-23k",
        "position": "深圳・南山区"
    },
    {
        "companyName": "湖北三新",
        "salary": "10k-20k",
        "position": "武汉・光谷"
    },
    {
        "companyName": "上海奔影网络科技有限公司",
        "salary": "15k-25k",
        "position": "上海・徐家汇"
    },
    {
        "companyName": "海万科技",
        "salary": "8k-14k",
        "position": "上海・浦东新…"
    },
    {
        "companyName": "三代人科技",
        "salary": "10k-17k",
        "position": "深圳・科技园"
    },
    {
        "companyName": "新云网",
        "salary": "9k-16k",
        "position": "长沙・岳麓区"
    },
    {
        "companyName": "阜极科技",
        "salary": "10k-20k",
        "position": "济南・杆石桥"
    },
    {
        "companyName": "金证股份",
        "salary": "10k-16k",
        "position": "深圳・福田区"
    },
    {
        "companyName": "星飞",
        "salary": "10k-15k",
        "position": "广州・天河区"
    },
    {
        "companyName": "云智汇（重庆）高新科技服务有限公司",
        "salary": "10k-15k",
        "position": "重庆・西永"
    },
    {
        "companyName": "红茄科技",
        "salary": "7k-10k",
        "position": "成都・高新区"
    },
    {
        "companyName": "通力互联",
        "salary": "10k-20k",
        "position": "北京・北京大…"
    },
    {
        "companyName": "无锡聚云科技有限公司",
        "salary": "6k-12k",
        "position": "无锡・滨湖区"
    },
    {
        "companyName": "迅联网络",
        "salary": "8k-15k",
        "position": "青岛・黄岛区"
    },
    {
        "companyName": "玩吧",
        "salary": "20k-35k",
        "position": "北京・东城区"
    },
    {
        "companyName": "海万科技",
        "salary": "9k-17k",
        "position": "上海・浦东新…"
    },
    {
        "companyName": "车伴",
        "salary": "6k-12k",
        "position": "长沙・天心区"
    },
    {
        "companyName": "浙江上士网络科技有限公司",
        "salary": "10k-15k",
        "position": "广州・东圃"
    },
    {
        "companyName": "贝盈达人",
        "salary": "15k-20k",
        "position": "杭州・余杭区"
    },
    {
        "companyName": "京华信息",
        "salary": "8k-15k",
        "position": "广州・天河区"
    },
    {
        "companyName": "中国联保",
        "salary": "8k-15k",
        "position": "深圳・龙岗区"
    },
    {
        "companyName": "鼎驰",
        "salary": "10k-15k",
        "position": "深圳・莲花二…"
    },
    {
        "companyName": "同业云",
        "salary": "15k-20k",
        "position": "上海・镇宁路"
    },
    {
        "companyName": "通力互联",
        "salary": "12k-20k",
        "position": "深圳・坂田"
    },
    {
        "companyName": "千展信息",
        "salary": "10k-15k",
        "position": "郑州・高新区"
    },
    {
        "companyName": "爱袋游戏",
        "salary": "10k-16k",
        "position": "南京・鼓楼区"
    },
    {
        "companyName": "新安金融",
        "salary": "8k-13k",
        "position": "合肥・包河区"
    },
    {
        "companyName": "创世乐享",
        "salary": "15k-25k",
        "position": "北京・海淀区"
    },
    {
        "companyName": "盈聚科技",
        "salary": "13k-20k",
        "position": "广州・新港"
    },
    {
        "companyName": "贝壳",
        "salary": "30k-60k",
        "position": "北京・上地"
    }
]